proxychains/__init__.py
proxychains-1.0.1.dist-info/LICENSE
proxychains-1.0.1.dist-info/METADATA
proxychains-1.0.1.dist-info/WHEEL
proxychains-1.0.1.dist-info/top_level.txt
proxychains-1.0.1.dist-info/RECORD
