Metadata-Version: 2.1
Name: proxychains
Version: 1.0.1
Summary: A python module for Chaining of Proxies.
Home-page: https://github.com/acuifex/proxychains
Author: acuifex
Author-email: proxychains@acuifex.ru
Classifier: Programming Language :: Python :: 3.10
Classifier: License :: OSI Approved :: GNU Affero General Public License v3 or later (AGPLv3+)
Classifier: Operating System :: OS Independent
License-File: LICENSE
Requires-Dist: urllib3
